Metadata-Version: 1.1
Name: Qasim
Version: 1.9.3
Summary: Generate diploid mutations and simulate HTS reads
Home-page: https://github.com/delocalizer/qasim
Author: Conrad Leonard
Author-email: conrad.leonard@hotmail.com
License: MIT
Platform: linux
Requires: numpy
Requires: setuptools
